[
  {
    "Enabled": false,
    "Prototype": "Metagame/PatrolBrooklyn/PatrolBrooklynMode.prototype",
    "Path": "States[]",
    "Description": "[Cowpocalypse (Special)] Add Cowpocalypse wave to Industry City Patrol",
    "ValueType": "PrototypeId",
    "Value": 4346653277293517379
  },
  {
    "Enabled": true,
    "Prototype": "Loot/Tables/Events/PowerupBuffLootMrHyde.prototype",
    "Path": "Choices[1].Power",
    "Description": "[A.R.M.O.R. Incursion (Weekly)] Fix condition removal power for the PowerupBuffLootMrHyde loot table",
    "ValueType": "PrototypeId",
    "Value": 13424308211504454457
  },
  {
    "Enabled": false,
    "Prototype": "Metagame/PatrolMidtown/PatrolMidtownMode.prototype",
    "Path": "ApplyStates[0]",
    "Description": "[Mystic Mayhem (Weekly)] Enable Mystic Mayhem bosses in Midtown Patrol",
    "ValueType": "PrototypeId",
    "Value": 714436682102808322
  },
  {
    "Enabled": true,
    "Prototype": "Loot/Tables/Mob/Bosses/DogTagsCurrencyTable.prototype",
    "Path": "NoDropPercent",
    "Description": "[Heroes for Hire (Weekly)] Set NoDropPercent for DogTagsCurrencyTable",
    "ValueType": "Float",
    "Value": 0.7
  },
  {
    "Enabled": true,
    "Prototype": "Loot/Tables/Mob/Bosses/DogTagsCurrencyTable.prototype",
    "Path": "Choices[0].PickMethod",
    "Description": "[Heroes for Hire (Weekly)] Set PickMethod to PickAll for DogTagsCurrencyTable",
    "ValueType": "Enum",
    "Value": "PickAll"
  },
  {
    "Enabled": true,
    "Prototype": "Loot/Tables/Mob/Bosses/DogTagsCurrencyTable.prototype",
    "Path": "Choices[0].Choices[0].Modifiers[]",
    "Description": "[Heroes for Hire (Weekly)] Add new LootRollRequireDropperKeywordPrototype for the first choice in DogTagsCurrencyTable",
    "ValueType": "Prototype",
    "Value": {
      "ParentDataRef": 17689313808028144366
    }
  },
  {
    "Enabled": true,
    "Prototype": "Loot/Tables/Mob/Bosses/DogTagsCurrencyTable.prototype",
    "Path": "Choices[0].Choices[0].Modifiers[0].Choices[]",
    "Description": "[Heroes for Hire (Weekly)] Restrict the first choice in DogTagsCurrencyTable to Mercenary",
    "ValueType": "PrototypeId",
    "Value": 12814754870629241647
  },
  {
    "Enabled": true,
    "Prototype": "Loot/Tables/Mob/Bosses/DogTagsCurrencyTable.prototype",
    "Path": "Choices[0].Choices[]",
    "Description": "[Heroes for Hire (Weekly)] Add the second LootDropItemPrototype to DogTagsCurrencyTable",
    "ValueType": "Prototype",
    "Value": {
      "ParentDataRef": 1071992662862269383,
      "Item": 4883437826439912008
    }
  },
  {
    "Enabled": true,
    "Prototype": "Loot/Tables/Mob/Bosses/DogTagsCurrencyTable.prototype",
    "Path": "Choices[0].Choices[1].Modifiers[]",
    "Description": "[Heroes for Hire (Weekly)] Add new LootRollRequireDropperKeywordPrototype for the second choice in DogTagsCurrencyTable",
    "ValueType": "Prototype",
    "Value": {
      "ParentDataRef": 17689313808028144366
    }
  },
  {
    "Enabled": true,
    "Prototype": "Loot/Tables/Mob/Bosses/DogTagsCurrencyTable.prototype",
    "Path": "Choices[0].Choices[1].Modifiers[0].Choices[]",
    "Description": "[Heroes for Hire (Weekly)] Restrict the second choice in DogTagsCurrencyTable to GangMember",
    "ValueType": "PrototypeId",
    "Value": 2198160877082579838
  },
  {
    "Enabled": true,
    "Prototype": "Loot/Tables/Mob/Bosses/DogTagsCurrencyTable.prototype",
    "Path": "Choices[0].Choices[]",
    "Description": "[Heroes for Hire (Weekly)] Add the third LootDropItemPrototype to DogTagsCurrencyTable",
    "ValueType": "Prototype",
    "Value": {
      "ParentDataRef": 1071992662862269383,
      "Item": 4883437826439912008
    }
  },
  {
    "Enabled": true,
    "Prototype": "Loot/Tables/Mob/Bosses/DogTagsCurrencyTable.prototype",
    "Path": "Choices[0].Choices[2].Modifiers[]",
    "Description": "[Heroes for Hire (Weekly)] Add new LootRollRequireDropperKeywordPrototype for the third choice in DogTagsCurrencyTable",
    "ValueType": "Prototype",
    "Value": {
      "ParentDataRef": 17689313808028144366
    }
  },
  {
    "Enabled": true,
    "Prototype": "Loot/Tables/Mob/Bosses/DogTagsCurrencyTable.prototype",
    "Path": "Choices[0].Choices[2].Modifiers[0].Choices[]",
    "Description": "[Heroes for Hire (Weekly)] Restrict the third choice in DogTagsCurrencyTable to Maggia",
    "ValueType": "PrototypeId",
    "Value": 11166669287029412303
  },
  {
    "Enabled": true,
    "Prototype": "Loot/Tables/Mob/Bosses/SpecialEventsTable.prototype",
    "Path": "Choices[]",
    "Description": "[Heroes for Hire (Weekly)] Add DogTagsCurrencyTable to SpecialEventsTable",
    "ValueType": "PrototypeDataRef",
    "Value": 16587225871960839503
  },
  {
    "Enabled": true,
    "Prototype": "Entity/Characters/Vendors/VendorTypes/VendorAvengersTowerEventTerminal.prototype",
    "Path": "Inventories[]",
    "Description": "[Heroes for Hire (Weekly)] Add VendorInventoryEntry for SpecialEventHeroesForHire to VendorAvengersTowerEventTerminal",
    "ValueType": "Prototype",
    "Value": {
      "ParentDataRef": 6775684286112470794,
      "LootTable": 13437915080456018735,
      "PlayerInventory": 15746332603173774372,
      "UseStartingAtVendorLevel": 1
    }
  },
  {
    "Enabled": true,
    "Prototype": "Loot/Tables/Mob/NeverMeltingCoreTable.prototype",
    "Path": "Modifiers[]",
    "Description": "[End of Summer (Weekly)] Apply MarkSpecial modifier to NeverMeltingCoreTable",
    "ValueType": "PrototypeDataRef",
    "Value": 6222183752544751228
  },
  {
    "Enabled": true,
    "Prototype": "Loot/Tables/Mob/SummerEventPowerUpTable.prototype",
    "Path": "Modifiers[]",
    "Description": "[End of Summer (Weekly)] Apply MarkSpecial modifier to SummerEventPowerUpTable",
    "ValueType": "PrototypeDataRef",
    "Value": 6222183752544751228
  },
  {
    "Enabled": true,
    "Prototype": "Loot/Tables/Mob/IceCreamBarTable.prototype",
    "Path": "Modifiers[]",
    "Description": "[End of Summer (Weekly)] Apply MarkSpecial modifier to IceCreamBarTable",
    "ValueType": "PrototypeDataRef",
    "Value": 6222183752544751228
  },
  {
    "Enabled": true,
    "Prototype": "Loot/Tables/Mob/Bosses/SpecialEventsTable.prototype",
    "Path": "Choices[]",
    "Description": "[End of Summer (Weekly)] Add NeverMeltingCoreTable to SpecialEventsTable",
    "ValueType": "PrototypeDataRef",
    "Value": 15190678659132494583
  },
  {
    "Enabled": true,
    "Prototype": "Loot/Tables/Mob/Bosses/SpecialEventsTable.prototype",
    "Path": "Choices[]",
    "Description": "[End of Summer (Weekly)] Add IceCreamBarTable to SpecialEventsTable",
    "ValueType": "PrototypeDataRef",
    "Value": 939198362985173164
  },
  {
    "Enabled": true,
    "Prototype": "Loot/Tables/Mob/Bosses/SpecialEventsTable.prototype",
    "Path": "Choices[]",
    "Description": "[End of Summer (Weekly)] Add SummerEventPowerUpTable to SpecialEventsTable",
    "ValueType": "PrototypeDataRef",
    "Value": 15744602249904722955
  },
  {
    "Enabled": true,
    "Prototype": "Loot/Tables/Mob/Bosses/PatrolBrooklyn/Subtable/SharedPatrolBrooklynBosses.prototype",
    "Path": "Choices[]",
    "Description": "[End of Summer (Weekly)] Add CupcakeTable to SharedPatrolBrooklynBosses",
    "ValueType": "PrototypeDataRef",
    "Value": 4766908907310157594
  },
  {
    "Enabled": true,
    "Prototype": "Loot/Tables/Mob/Bosses/PatrolBrooklyn/Subtable/SharedPatrolBrooklynBossesCosmic.prototype",
    "Path": "Choices[]",
    "Description": "[End of Summer (Weekly)] Add CupcakeTable to SharedPatrolBrooklynBossesCosmic",
    "ValueType": "PrototypeDataRef",
    "Value": 4766908907310157594
  },
  {
    "Enabled": true,
    "Prototype": "Loot/Tables/Mob/Bosses/PatrolHightown/Subtable/SharedPatrolHightownBosses.prototype",
    "Path": "Choices[]",
    "Description": "[End of Summer (Weekly)] Add CupcakeTable to SharedPatrolHightownBosses",
    "ValueType": "PrototypeDataRef",
    "Value": 4766908907310157594
  },
  {
    "Enabled": true,
    "Prototype": "Loot/Tables/Mob/Bosses/PatrolHightown/Subtable/SharedPatrolHightownBossesCosmic.prototype",
    "Path": "Choices[]",
    "Description": "[End of Summer (Weekly)] Add CupcakeTable to SharedPatrolHightownBossesCosmic",
    "ValueType": "PrototypeDataRef",
    "Value": 4766908907310157594
  },
  {
    "Enabled": true,
    "Prototype": "Loot/Tables/Mob/Bosses/PatrolMidtown/Subtable/SharedPatrolMidtownBosses.prototype",
    "Path": "Choices[]",
    "Description": "[End of Summer (Weekly)] Add CupcakeTable to SharedPatrolMidtownBosses",
    "ValueType": "PrototypeDataRef",
    "Value": 4766908907310157594
  },
  {
    "Enabled": true,
    "Prototype": "Loot/Tables/Mob/Bosses/PatrolMidtown/Subtable/SharedPatrolMidtownBossesCosmic.prototype",
    "Path": "Choices[]",
    "Description": "[End of Summer (Weekly)] Add CupcakeTable to SharedPatrolMidtownBossesCosmic",
    "ValueType": "PrototypeDataRef",
    "Value": 4766908907310157594
  },
  {
    "Enabled": true,
    "Prototype": "Entity/Characters/Vendors/VendorTypes/VendorAvengersTowerEventTerminal.prototype",
    "Path": "Inventories[]",
    "Description": "[End of Summer (Weekly)] Add VendorInventoryEntry for SpecialEventSummer to VendorAvengersTowerEventTerminal",
    "ValueType": "Prototype",
    "Value": {
      "ParentDataRef": 6775684286112470794,
      "LootTable": 16485753690354620499,
      "PlayerInventory": 15746332603173774372,
      "UseStartingAtVendorLevel": 1
    }
  },
  {
    "Enabled": true,
    "Prototype": "Entity/Characters/Vendors/VendorTypes/VendorAvengersTowerEventTerminal.prototype",
    "Path": "Inventories[]",
    "Description": "[The Wealth of Kings County (Weekly)] Add VendorInventoryEntry for SpecialEventBundlesofCash to VendorAvengersTowerEventTerminal",
    "ValueType": "Prototype",
    "Value": {
      "ParentDataRef": 6775684286112470794,
      "LootTable": 2760518776469920539,
      "PlayerInventory": 15746332603173774372,
      "UseStartingAtVendorLevel": 1
    }
  },
  {
    "Enabled": false,
    "Prototype": "Loot/Tables/Mob/Bosses/SpecialEventsTable.prototype",
    "Path": "Choices[]",
    "Description": "[Australia Day (January 26)] Add AustraliaDayTable to SpecialEventsTable",
    "ValueType": "PrototypeDataRef",
    "Value": 5244862316186571775
  },
  {
    "Enabled": false,
    "Prototype": "Loot/Tables/Mob/Bosses/SpecialEventsTable.prototype",
    "Path": "Choices[]",
    "Description": "[Valentine's Day (February 14)] Add [ValentinesEventPowerupTable, VDayTable] to SpecialEventsTable",
    "ValueType": "PrototypeDataRef[]",
    "Value": [ 1089767944042846312, 7378732117961543855 ]
  },
  {
    "Enabled": false,
    "Prototype": "Loot/Tables/Mob/Bosses/SpecialEventsTable.prototype",
    "Path": "Choices[]",
    "Description": "[Lunar New Year (February 17)] Add LunarNewYearTable to SpecialEventsTable",
    "ValueType": "PrototypeDataRef",
    "Value": 577300379588563992
  },
  {
    "Enabled": true,
    "Prototype": "Loot/Tables/Mob/Bosses/SpecialEventsTable.prototype",
    "Path": "Choices[]",
    "Description": "[St Patrick's Day (March 17)] Add StPatricksEventPowerUpTable to SpecialEventsTable",
    "ValueType": "PrototypeDataRef",
    "Value": 7592276506700879991
  },
  {
    "Enabled": false,
    "Prototype": "Loot/Tables/Mob/Bosses/EndgameDailies/Terminals/OdinsPalace/KurseTerminalLoot.prototype",
    "Path": "Choices[]",
    "Description": "[April Fools Day (April 1)] Add AprilFoolsTable to KurseTerminalLoot",
    "ValueType": "PrototypeDataRef",
    "Value": 13919124432858911542
  },
  {
    "Enabled": false,
    "Prototype": "Loot/Tables/Mob/Bosses/SpecialEventsTable.prototype",
    "Path": "Choices[]",
    "Description": "[Anniversary (June 4)] Add AnniversaryCakeDropTable to SpecialEventsTable",
    "ValueType": "PrototypeDataRef",
    "Value": 10570310015585883894
  },
  {
    "Enabled": false,
    "Prototype": "Entity/Characters/Vendors/VendorTypes/VendorAvengersTowerEventTerminal.prototype",
    "Path": "Inventories[]",
    "Description": "[Anniversary (June 4)] Add VendorInventoryEntry for Anniversary2016VendorLootTable to VendorAvengersTowerEventTerminal",
    "ValueType": "Prototype",
    "Value": {
      "ParentDataRef": 6775684286112470794,
      "LootTable": 6619300753712815238,
      "PlayerInventory": 15746332603173774372,
      "UseStartingAtVendorLevel": 1
    }
  },
  {
    "Enabled": true,
    "Prototype": "Entity/Characters/Vendors/VendorTypes/VendorAvengersTowerEventTerminal.prototype",
    "Path": "Inventories[]",
    "Description": "[Anniversary (June 4)] Add VendorInventoryEntry for Anniversary2017VendorLootTable to VendorAvengersTowerEventTerminal (keep this last to allow Anniversary2017 to override other events)",
    "ValueType": "Prototype",
    "Value": {
      "ParentDataRef": 6775684286112470794,
      "LootTable": 13601394654621801607,
      "PlayerInventory": 15746332603173774372,
      "UseStartingAtVendorLevel": 1
    }
  },
  {
    "Enabled": false,
    "Prototype": "Loot/Tables/Mob/Bosses/SpecialEventsTable.prototype",
    "Path": "Choices[]",
    "Description": "[Halloween (October 31)] Add HalloweenPowerupTable to SpecialEventsTable",
    "ValueType": "PrototypeDataRef",
    "Value": 7708957262339380684
  }
]