[
  {
    "Enabled": true,
    "Prototype": "Entity/Items/Insignias/Prototypes/Insignia022.prototype",
    "Path": "LootDropWeightMultiplier",
    "Description": "Allow Insignia of Mister Fantastic to drop.",
    "ValueType": "Float",
    "Value": 1.0
  },
  {
    "Enabled": true,
    "Prototype": "Entity/Items/Insignias/Prototypes/Insignia024.prototype",
    "Path": "LootDropWeightMultiplier",
    "Description": "Allow Insignia of Invisible Woman to drop.",
    "ValueType": "Float",
    "Value": 1.0
  },
  {
    "Enabled": true,
    "Prototype": "Entity/Items/Insignias/Prototypes/Insignia028.prototype",
    "Path": "LootDropWeightMultiplier",
    "Description": "Allow Insignia of the Thing to drop.",
    "ValueType": "Float",
    "Value": 1.0
  },
  {
    "Enabled": true,
    "Prototype": "Entity/Items/Insignias/Prototypes/Insignia030.prototype",
    "Path": "LootDropWeightMultiplier",
    "Description": "Allow Insignia of She-Hulk to drop.",
    "ValueType": "Float",
    "Value": 1.0
  },
  {
    "Enabled": true,
    "Prototype": "Entity/Items/Insignias/Prototypes/Insignia031.prototype",
    "Path": "LootDropWeightMultiplier",
    "Description": "Allow Insignia of HERBIE to drop.",
    "ValueType": "Float",
    "Value": 1.0
  },
  {
    "Enabled": true,
    "Prototype": "Entity/Items/Insignias/Prototypes/Insignia032.prototype",
    "Path": "LootDropWeightMultiplier",
    "Description": "Allow Insignia of Crystal to drop.",
    "ValueType": "Float",
    "Value": 1.0
  },
  {
    "Enabled": true,
    "Prototype": "Entity/Items/Insignias/Prototypes/Insignia033.prototype",
    "Path": "LootDropWeightMultiplier",
    "Description": "Allow Insignia of Frankie Raye to drop.",
    "ValueType": "Float",
    "Value": 1.0
  },
  {
    "Enabled": true,
    "Prototype": "Entity/Items/Insignias/Prototypes/Insignia034.prototype",
    "Path": "LootDropWeightMultiplier",
    "Description": "Allow Insignia of Medusa to drop.",
    "ValueType": "Float",
    "Value": 1.0
  },
  {
    "Enabled": true,
    "Prototype": "Loot/Tables/ItemType/SpecialsArtifactsRespec.prototype",
    "Path": "Choices[0].NoDropPercent",
    "Description": "Revert the 99.9% artifact drop rate reduction added with SHIELD Supply Drops.",
    "ValueType": "Float",
    "Value": 0.0
  }
]